Pruning_Engine/__init__.py
Pruning_Engine/pruning_engine.py
Pruning_Engine/pruning_engine_base.py
Pruning_Engine/Pruning_criterion/__init__.py
Pruning_Engine/Pruning_criterion/KMean/K_Distance.py
Pruning_Engine/Pruning_criterion/KMean/K_L1norm.py
Pruning_Engine/Pruning_criterion/KMean/K_Taylor.py
Pruning_Engine/Pruning_criterion/KMean/Kmean_base.py
Pruning_Engine/Pruning_criterion/KMean/__init__.py
Pruning_Engine/Pruning_criterion/L1norm/L1norm.py
Pruning_Engine/Pruning_criterion/L1norm/__init__.py
Pruning_Engine/Pruning_criterion/Taylor/Taylor.py
Pruning_Engine/Pruning_criterion/Taylor/__init__.py
Pruning_Engine_SFSU_MICLab-1.0.4.dist-info/METADATA
Pruning_Engine_SFSU_MICLab-1.0.4.dist-info/WHEEL
Pruning_Engine_SFSU_MICLab-1.0.4.dist-info/top_level.txt
Pruning_Engine_SFSU_MICLab-1.0.4.dist-info/RECORD
