Metadata-Version: 2.1
Name: Pruning_Engine_SFSU_MICLab
Version: 1.0.4
Summary: Pruning Engine for CNN
Author-email: Zhenyu Lin <zlin4@mail.sfsu.edu>
License: MIT License
Project-URL: Homepage, https://github.com/MIC-Laboratory/CNN-Pruning-Engine
Project-URL: Issues, https://github.com/MIC-Laboratory/CNN-Pruning-Engine/issues
Classifier: Programming Language :: Python :: 3
Classifier: License :: OSI Approved :: MIT License
Classifier: Operating System :: OS Independent
Requires-Python: >=3.9
Requires-Dist: numpy
Requires-Dist: Pillow
Requires-Dist: PyYAML
Requires-Dist: scikit-learn
Requires-Dist: thop
Requires-Dist: torch
Requires-Dist: torchvision
Requires-Dist: tqdm
